<annotation>
	<folder>french_fries</folder>
	<filename>966854.jpg</filename>
	<path>C:\Users\Utilisateur\OneDrive\Bureau\Info\BUT 3\S501\AiTraining\Labelling\toLabel\french_fries\966854.jpg</path>
	<source>
		<database>Unknown</database>
	</source>
	<size>
		<width>512</width>
		<height>512</height>
		<depth>3</depth>
	</size>
	<segmented>0</segmented>
	<object>
		<name>french fries</name>
		<pose>Unspecified</pose>
		<truncated>0</truncated>
		<difficult>0</difficult>
		<bndbox>
			<xmin>110</xmin>
			<ymin>14</ymin>
			<xmax>509</xmax>
			<ymax>482</ymax>
		</bndbox>
	</object>
</annotation>
