<annotation>
	<folder>pancakes</folder>
	<filename>729861.jpg</filename>
	<path>C:\Users\dotto\Desktop\Matis\Documents\BUT\3A\S5\SAE\S501\AiTraining\Labelling\toLabel\pancakes\729861.jpg</path>
	<source>
		<database>Unknown</database>
	</source>
	<size>
		<width>512</width>
		<height>512</height>
		<depth>3</depth>
	</size>
	<segmented>0</segmented>
	<object>
		<name>pancakes</name>
		<pose>Unspecified</pose>
		<truncated>0</truncated>
		<difficult>0</difficult>
		<bndbox>
			<xmin>3</xmin>
			<ymin>11</ymin>
			<xmax>510</xmax>
			<ymax>511</ymax>
		</bndbox>
	</object>
</annotation>
