<annotation>
	<folder>hamburger</folder>
	<filename>1007277.jpg</filename>
	<path>C:\Users\Utilisateur\OneDrive\Bureau\Info\BUT 3\S501\AiTraining\Labelling\toLabel\hamburger\1007277.jpg</path>
	<source>
		<database>Unknown</database>
	</source>
	<size>
		<width>512</width>
		<height>307</height>
		<depth>3</depth>
	</size>
	<segmented>0</segmented>
	<object>
		<name>hamburger</name>
		<pose>Unspecified</pose>
		<truncated>1</truncated>
		<difficult>0</difficult>
		<bndbox>
			<xmin>1</xmin>
			<ymin>10</ymin>
			<xmax>288</xmax>
			<ymax>307</ymax>
		</bndbox>
	</object>
</annotation>
