<annotation>
	<folder>hamburger</folder>
	<filename>2534877.jpg</filename>
	<path>C:\Users\Utilisateur\OneDrive\Bureau\Info\BUT 3\S501\AiTraining\Labelling\toLabel\hamburger\2534877.jpg</path>
	<source>
		<database>Unknown</database>
	</source>
	<size>
		<width>512</width>
		<height>512</height>
		<depth>3</depth>
	</size>
	<segmented>0</segmented>
	<object>
		<name>hamburger</name>
		<pose>Unspecified</pose>
		<truncated>0</truncated>
		<difficult>0</difficult>
		<bndbox>
			<xmin>208</xmin>
			<ymin>261</ymin>
			<xmax>446</xmax>
			<ymax>509</ymax>
		</bndbox>
	</object>
</annotation>
