<annotation>
	<folder>spaghetti_carbonara</folder>
	<filename>641417.jpg</filename>
	<path>C:\Users\Arthur\Documents\GitHub\S501\AiTraining\Labelling\toLabel\spaghetti_carbonara\641417.jpg</path>
	<source>
		<database>Unknown</database>
	</source>
	<size>
		<width>512</width>
		<height>512</height>
		<depth>3</depth>
	</size>
	<segmented>0</segmented>
	<object>
		<name>spaghetti carbonara</name>
		<pose>Unspecified</pose>
		<truncated>0</truncated>
		<difficult>0</difficult>
		<bndbox>
			<xmin>21</xmin>
			<ymin>36</ymin>
			<xmax>510</xmax>
			<ymax>499</ymax>
		</bndbox>
	</object>
</annotation>
